indicomb2/__init__.py
indicomb2/contribution.py
indicomb2/event.py
indicomb2/indicomb2.py
indicomb2/markdown.py
indicomb2/meetings.py
indicomb2/requests.py
indicomb2/search.py
indicomb2-0.6.dist-info/METADATA
indicomb2-0.6.dist-info/WHEEL
indicomb2-0.6.dist-info/entry_points.txt
indicomb2-0.6.dist-info/top_level.txt
indicomb2-0.6.dist-info/RECORD
