Metadata-Version: 2.4
Name: indicomb2
Version: 0.6
Summary: Faster indicomb with mkdocs markdown support
License: MIT
Requires-Python: >=3.10
Requires-Dist: pyyaml>=6.0.2
Requires-Dist: requests>=2.32.3
Provides-Extra: dev
Requires-Dist: pytest>=8.3.3; extra == "dev"
Requires-Dist: ruff>=0.6.8; extra == "dev"
